dataframe_to_image/dataframe_to_image.py
dataframe_to_image-0.0.1.dist-info/LICENSE
dataframe_to_image-0.0.1.dist-info/METADATA
dataframe_to_image-0.0.1.dist-info/WHEEL
dataframe_to_image-0.0.1.dist-info/top_level.txt
dataframe_to_image-0.0.1.dist-info/RECORD
