Metadata-Version: 2.1
Name: dataframe-to-image
Version: 0.0.1
Summary: Convert Pandas DataFrame to Image
Home-page: https://github.com/imaadmkhan1/dataframe_to_image
Author: Imaad Mohamed Khan
Author-email: imaadmkhan1@gmail.com
License: MIT
Platform: UNKNOWN
Classifier: License :: OSI Approved :: MIT License
Classifier: Programming Language :: Python :: 3
Classifier: Programming Language :: Python :: 3.7
License-File: LICENSE
Requires-Dist: pandas
Requires-Dist: numpy
Requires-Dist: matplotlib
Requires-Dist: plotly
